{
  "name": "core::<array::iter::IntoIter<T, N> as clone::Clone>::clone",
  "span": "$library/core/src/array/iter.rs:19:10: 19:15",
  "safe": true,
  "callees": {
    "core::clone::Clone::clone": {
      "safe": true,
      "adt": {}
    }
  },
  "adts": {
    "mem::manually_drop::ManuallyDrop": [
      "Ref",
      "Plain"
    ],
    "array::iter::IntoIter": [
      "DerefVariantField(VariantIdx(None)-FieldIdx(Some(0)))",
      "Plain",
      "Ref"
    ]
  },
  "path": {
    "type": "Local",
    "path": "core::<array::iter::IntoIter<T, N> as clone::Clone>::clone"
  }
}