{
  "name": "core::core_arch::arm_shared::neon::generated::vld4q_s8",
  "span": "$library/core/src/../../stdarch/crates/core_arch/src/arm_shared/neon/generated.rs:26050:1: 26050:52",
  "safe": false,
  "callees": {
    "core::core_arch::arm_shared::neon::generated::vld4q_s8::_vld4q_s8": {
      "safe": false,
      "adt": {}
    }
  },
  "adts": {
    "core_arch::arm_shared::neon::int8x16x4_t": {
      "kind": "Constructor",
      "field": {}
    }
  },
  "path": {
    "type": "Local",
    "path": "core::core_arch::arm_shared::neon::generated::vld4q_s8"
  }
}