{
  "name": "core::core_arch::arm_shared::neon::generated::vrev16q_s8",
  "span": "$library/core/src/../../stdarch/crates/core_arch/src/arm_shared/neon/generated.rs:57212:1: 57212:45",
  "safe": false,
  "callees": {
    "core::intrinsics::simd::simd_shuffle": {
      "safe": false,
      "adt": {}
    }
  },
  "adts": {
    "core_arch::arm_shared::neon::int8x16_t": [
      "Plain"
    ]
  },
  "path": {
    "type": "Local",
    "path": "core::core_arch::arm_shared::neon::generated::vrev16q_s8"
  }
}