{
  "name": "std::path::<impl core::convert::From<path::PathBuf> for alloc_crate::rc::Rc<path::Path>>::from",
  "span": "$library/std/src/path.rs:2163:5: 2163:36",
  "safe": true,
  "callees": {
    "std::path::PathBuf::into_os_string": {
      "safe": true,
      "adt": {
        "ffi::os_str::OsString": "Constructor"
      }
    },
    "core::convert::From::from": {
      "safe": true,
      "adt": {}
    },
    "alloc_crate::rc::Rc::<T>::into_raw": {
      "safe": true,
      "adt": {}
    },
    "alloc_crate::rc::Rc::<T>::from_raw": {
      "safe": false,
      "adt": {}
    }
  },
  "adts": {
    "path::PathBuf": [
      "Plain"
    ],
    "ffi::os_str::OsString": [
      "Plain"
    ],
    "alloc_crate::rc::Rc": [
      "Plain"
    ]
  },
  "path": {
    "type": "Local",
    "path": "std::path::<impl core::convert::From<path::PathBuf> for alloc_crate::rc::Rc<path::Path>>::from"
  }
}