{
  "name": "alloc::<bstr::ByteString as core::ops::Index<core::ops::RangeTo<usize>>>::index",
  "span": "$library/alloc/src/bstr.rs:388:5: 388:51",
  "safe": true,
  "callees": {
    "core::ops::Index::index": {
      "safe": true,
      "tags": {
        "tags": [],
        "spec": {},
        "docs": []
      },
      "adt": {}
    },
    "core::bstr::ByteStr::from_bytes": {
      "safe": true,
      "tags": {
        "tags": [
          {
            "tag": {
              "typ": null,
              "name": "hidden"
            },
            "args": []
          }
        ],
        "spec": {},
        "docs": [
          "* hidden\n"
        ]
      },
      "adt": {}
    }
  },
  "adts": {
    "vec::Vec": [
      "Ref"
    ],
    "bstr::ByteString": [
      "DerefVariantField(VariantIdx(None)-FieldIdx(Some(0)))",
      "Ref"
    ],
    "core::ops::RangeTo": [
      "Plain"
    ],
    "core::bstr::ByteStr": [
      "Ref"
    ]
  },
  "path": {
    "type": "Local",
    "path": "alloc::<bstr::ByteString as core::ops::Index<core::ops::RangeTo<usize>>>::index"
  },
  "tags": {
    "tags": [],
    "spec": {},
    "docs": []
  }
}