{
  "name": "std::sys::pal::unix::stack_overflow::imp::init",
  "span": "$library/std/src/sys/pal/unix/stack_overflow.rs:152:5: 152:25",
  "safe": false,
  "callees": {
    "std::sys::pal::unix::os::page_size": {
      "safe": true,
      "adt": {}
    },
    "core::sync::atomic::AtomicUsize::store": {
      "safe": true,
      "adt": {}
    },
    "std::sys::pal::unix::stack_overflow::imp::install_main_guard": {
      "safe": false,
      "adt": {
        "core::option::Option": {
          "kind": "Constructor",
          "field": {}
        },
        "core::ops::Range": {
          "kind": "Constructor",
          "field": {}
        }
      }
    },
    "core::mem::zeroed": {
      "safe": false,
      "adt": {}
    },
    "core::iter::IntoIterator::into_iter": {
      "safe": true,
      "adt": {}
    },
    "core::iter::Iterator::next": {
      "safe": true,
      "adt": {}
    },
    "core::ptr::null_mut": {
      "safe": true,
      "adt": {}
    },
    "libc::sigaction": {
      "safe": false,
      "adt": {}
    },
    "core::sync::atomic::AtomicBool::load": {
      "safe": true,
      "adt": {}
    },
    "core::sync::atomic::AtomicBool::store": {
      "safe": true,
      "adt": {}
    },
    "std::sys::pal::unix::stack_overflow::imp::make_handler": {
      "safe": false,
      "adt": {
        "sys::pal::unix::stack_overflow::Handler": {
          "kind": "Constructor",
          "field": {}
        }
      }
    },
    "core::sync::atomic::AtomicPtr::<T>::store": {
      "safe": true,
      "adt": {}
    },
    "core::mem::forget": {
      "safe": true,
      "adt": {}
    },
    "core::option::Option::<T>::take": {
      "safe": true,
      "adt": {}
    },
    "std::sys::pal::unix::stack_overflow::thread_info::set_current_info": {
      "safe": true,
      "adt": {}
    },
    "std::sys::pal::unix::stack_overflow::imp::signal_handler": {
      "safe": false,
      "adt": {}
    }
  },
  "adts": {
    "core::sync::atomic::AtomicUsize": [
      "Ref"
    ],
    "core::sync::atomic::Ordering": [
      "Plain"
    ],
    "core::option::Option": [
      "Plain",
      "Unknown([Downcast(VariantIdx(1, ThreadLocalIndex)), Field(0, Ty { id: 5483, kind: RigidTy(Ref(Region { kind: ReErased }, Ty { id: 44, kind: RigidTy(Int(I32)) }, Not)) })])",
      "MutRef",
      "Unknown([Downcast(VariantIdx(1, ThreadLocalIndex)), Field(0, Ty { id: 3405, kind: RigidTy(Adt(AdtDef(DefId { id: 5850, name: \"core::ops::Range\" }), GenericArgs([Type(Ty { id: 393, kind: RigidTy(Uint(Usize)) })]))) })])"
    ],
    "libc::sigaction": [
      "Plain",
      "MutRef",
      "Deref",
      "Unknown([Field(0, Ty { id: 393, kind: RigidTy(Uint(Usize)) })])",
      "Unknown([Field(2, Ty { id: 44, kind: RigidTy(Int(I32)) })])",
      "Ref"
    ],
    "core::slice::Iter": [
      "Plain",
      "MutRef"
    ],
    "core::sync::atomic::AtomicBool": [
      "Ref"
    ],
    "sys::pal::unix::stack_overflow::Handler": [
      "Plain",
      "Unknown([Field(0, Ty { id: 1128, kind: RigidTy(RawPtr(Ty { id: 1135, kind: RigidTy(Adt(AdtDef(DefId { id: 8156, name: \"libc::c_void\" }), GenericArgs([]))) }, Mut)) })])"
    ],
    "core::sync::atomic::AtomicPtr": [
      "Ref"
    ],
    "core::ops::Range": [
      "Plain"
    ]
  },
  "path": {
    "type": "Local",
    "path": "std::sys::pal::unix::stack_overflow::imp::init"
  }
}