{
  "name": "<sync::once_lock::OnceLock<T> as core::cmp::PartialEq>::eq",
  "safe": true,
  "callees": {
    "sync::once_lock::OnceLock::<T>::get": {
      "safe": true,
      "tags": {
        "tags": [],
        "spec": {},
        "docs": []
      },
      "doc": " Gets the reference to the underlying value.\n\n Returns `None` if the cell is uninitialized, or being initialized.\n This method never blocks.\n",
      "adt": {
        "sync::once_lock::OnceLock": "ImmutableAsArgument",
        "core::option::Option": "Constructor"
      }
    },
    "core::cmp::PartialEq::eq": {
      "safe": true,
      "tags": {
        "tags": [],
        "spec": {},
        "docs": []
      },
      "doc": " Tests for `self` and `other` values to be equal, and is used by `==`.\n",
      "adt": {}
    }
  },
  "adts": {
    "sync::once_lock::OnceLock": [
      "Ref"
    ],
    "core::option::Option": [
      "Plain",
      "Ref"
    ]
  },
  "path": {
    "type": "Local",
    "path": "std::<sync::once_lock::OnceLock<T> as core::cmp::PartialEq>::eq"
  },
  "span": "/home/gh-zjp-CN/.rustup/toolchains/nightly-2025-12-06-aarch64-unknown-linux-gnu/lib/rustlib/src/rust/library/std/src/sync/once_lock.rs:680:5: 682:6",
  "src": "fn eq(&self, other: &OnceLock<T>) -> bool {\n        self.get() == other.get()\n    }",
  "mir": "fn <sync::once_lock::OnceLock<T> as core::cmp::PartialEq>::eq(_1: &sync::once_lock::OnceLock<T>, _2: &sync::once_lock::OnceLock<T>) -> bool {\n    let mut _0: bool;\n    let mut _3: &core::option::Option<&T>;\n    let  _4: core::option::Option<&T>;\n    let mut _5: &core::option::Option<&T>;\n    let  _6: core::option::Option<&T>;\n    debug self => _1;\n    debug other => _2;\n    bb0: {\n        StorageLive(_3);\n        StorageLive(_4);\n        _4 = sync::once_lock::OnceLock::<T>::get(_1) -> [return: bb1, unwind unreachable];\n    }\n    bb1: {\n        _3 = &_4;\n        StorageLive(_5);\n        StorageLive(_6);\n        _6 = sync::once_lock::OnceLock::<T>::get(_2) -> [return: bb2, unwind unreachable];\n    }\n    bb2: {\n        _5 = &_6;\n        _0 = <core::option::Option<&T> as core::cmp::PartialEq>::eq(move _3, move _5) -> [return: bb3, unwind unreachable];\n    }\n    bb3: {\n        StorageDead(_6);\n        StorageDead(_5);\n        StorageDead(_4);\n        StorageDead(_3);\n        return;\n    }\n}\n",
  "doc": " Equality for two `OnceLock`s.\n\n Two `OnceLock`s are equal if they either both contain values and their\n values are equal, or if neither contains a value.\n\n # Examples\n\n ```\n use std::sync::OnceLock;\n\n let five = OnceLock::new();\n five.set(5).unwrap();\n\n let also_five = OnceLock::new();\n also_five.set(5).unwrap();\n\n assert!(five == also_five);\n\n assert!(OnceLock::<u32>::new() == OnceLock::<u32>::new());\n ```\n",
  "tags": {
    "tags": [],
    "spec": {},
    "docs": []
  }
}