{
  "name": "sys::sync::rwlock::futex::has_reached_max_readers",
  "safe": true,
  "callees": {},
  "adts": {},
  "path": {
    "type": "Local",
    "path": "std::sys::sync::rwlock::futex::has_reached_max_readers"
  },
  "span": "/home/gh-zjp-CN/.rustup/toolchains/nightly-2025-12-06-aarch64-unknown-linux-gnu/lib/rustlib/src/rust/library/std/src/sys/sync/rwlock/futex.rs:76:1: 78:2",
  "src": "fn has_reached_max_readers(state: Primitive) -> bool {\n    state & MASK == MAX_READERS\n}",
  "mir": "fn sys::sync::rwlock::futex::has_reached_max_readers(_1: u32) -> bool {\n    let mut _0: bool;\n    let mut _2: u32;\n    debug state => _1;\n    bb0: {\n        StorageLive(_2);\n        _2 = BitAnd(_1, sys::sync::rwlock::futex::MASK);\n        _0 = Eq(move _2, sys::sync::rwlock::futex::MAX_READERS);\n        StorageDead(_2);\n        return;\n    }\n}\n",
  "doc": "",
  "tags": {
    "tags": [],
    "spec": {},
    "docs": []
  }
}