{
  "name": "<boxed::Box<F, A> as core::ops::Fn<Args>>::call",
  "safe": true,
  "callees": {
    "core::ops::Fn::call": {
      "safe": true,
      "tags": {
        "tags": [],
        "spec": {},
        "docs": []
      },
      "doc": " Performs the call operation.\n",
      "adt": {}
    }
  },
  "adts": {
    "boxed::Box": [
      "Plain",
      "Deref",
      "Unknown([Field(0, Ty { id: 1477, kind: RigidTy(Adt(AdtDef(DefId { id: 2645, name: \"core::ptr::Unique\" }), GenericArgs([Type(Ty { id: 1485, kind: Param(ParamTy { index: 1, name: \"F\" }) })]))) }), Field(0, Ty { id: 1478, kind: RigidTy(Adt(AdtDef(DefId { id: 2619, name: \"core::ptr::NonNull\" }), GenericArgs([Type(Ty { id: 1485, kind: Param(ParamTy { index: 1, name: \"F\" }) })]))) })])",
      "Ref"
    ]
  },
  "path": {
    "type": "Local",
    "path": "alloc::<boxed::Box<F, A> as core::ops::Fn<Args>>::call"
  },
  "span": "/home/gh-zjp-CN/.rustup/toolchains/nightly-2025-12-06-aarch64-unknown-linux-gnu/lib/rustlib/src/rust/library/alloc/src/boxed.rs:2219:5: 2221:6",
  "src": "extern \"rust-call\" fn call(&self, args: Args) -> Self::Output {\n        <F as Fn<Args>>::call(self, args)\n    }",
  "mir": "fn <boxed::Box<F, A> as core::ops::Fn<Args>>::call(_1: &boxed::Box<F, A>, _2: Args) -> <F as core::ops::FnOnce<Args>>::Output {\n    let mut _0: <F as core::ops::FnOnce<Args>>::Output;\n    let mut _3: &F;\n    let mut _4: boxed::Box<F, A>;\n    let mut _5: *const F;\n    debug self => _1;\n    debug args => _2;\n    bb0: {\n        StorageLive(_3);\n        _4 = (*_1);\n        _5 = ((_4.0: core::ptr::Unique<F>).0: core::ptr::NonNull<F>) as *const F;\n        _3 = &(*_5);\n        _0 = <F as core::ops::Fn<Args>>::call(move _3, _2) -> [return: bb1, unwind unreachable];\n    }\n    bb1: {\n        StorageDead(_3);\n        return;\n    }\n}\n",
  "doc": "",
  "tags": {
    "tags": [],
    "spec": {},
    "docs": []
  }
}