{
  "name": "core::str::CharEscapeUnicode",
  "constructors": [
    "core::<str::CharEscapeUnicode as clone::Clone>::clone"
  ],
  "access_self_as_arg": {
    "read": [
      "core::<str::CharEscapeUnicode as clone::Clone>::clone",
      "core::<str::CharEscapeUnicode as ops::function::Fn<(char,)>>::call",
      "core::<str::CharEscapeUnicode as ops::function::FnMut<(char,)>>::call_mut",
      "core::<str::CharEscapeUnicode as ops::function::FnOnce<(char,)>>::call_once"
    ],
    "write": [
      "core::<str::CharEscapeUnicode as ops::function::FnMut<(char,)>>::call_mut",
      "core::<str::CharEscapeUnicode as ops::function::FnMut<(char,)>>::call_mut"
    ],
    "other": [
      "core::<str::CharEscapeUnicode as ops::function::FnOnce<(char,)>>::call_once"
    ]
  },
  "access_self_as_locals": {
    "read": [],
    "write": [],
    "other": []
  },
  "access_field": [],
  "span": "$library/core/src/internal_macros.rs:81:13: 81:26",
  "src": "struct $Name;",
  "kind": "Struct",
  "doc_adt": "",
  "variant_fields": {}
}