{
  "name": "arch::cpu::context::CpuException::type_",
  "safe": true,
  "callees": {},
  "adts": {
    "arch::cpu::context::CpuException": [
      "Deref",
      "Ref"
    ],
    "arch::cpu::context::CpuExceptionType": [
      "Plain"
    ]
  },
  "path": 372,
  "span": "ostd/src/arch/x86/cpu/context/mod.rs:201:5: 210:6",
  "src": "const fn type_(&self) -> CpuExceptionType {\n        match self {\n            Self::Debug => CpuExceptionType::FaultOrTrap,\n            Self::NonMaskableInterrupt => CpuExceptionType::Interrupt,\n            Self::BreakPoint | Self::Overflow => CpuExceptionType::Trap,\n            Self::DoubleFault | Self::MachineCheck => CpuExceptionType::Abort,\n            Self::Reserved => CpuExceptionType::Reserved,\n            _ => CpuExceptionType::Fault,\n        }\n    }",
  "mir": "fn arch::cpu::context::CpuException::type_(_1: &arch::cpu::context::CpuException) -> arch::cpu::context::CpuExceptionType {\n    let mut _0: arch::cpu::context::CpuExceptionType;\n    let mut _2: isize;\n    debug self => _1;\n    bb0: {\n        _2 = discriminant((*_1));\n        switchInt(move _2) -> [1: bb6, 2: bb5, 3: bb4, 4: bb4, 8: bb3, 17: bb3, 24: bb2, otherwise: bb1];\n    }\n    bb1: {\n        _0 = arch::cpu::context::CpuExceptionType::Fault;\n        goto -> bb7;\n    }\n    bb2: {\n        _0 = arch::cpu::context::CpuExceptionType::Reserved;\n        goto -> bb7;\n    }\n    bb3: {\n        _0 = arch::cpu::context::CpuExceptionType::Abort;\n        goto -> bb7;\n    }\n    bb4: {\n        _0 = arch::cpu::context::CpuExceptionType::Trap;\n        goto -> bb7;\n    }\n    bb5: {\n        _0 = arch::cpu::context::CpuExceptionType::Interrupt;\n        goto -> bb7;\n    }\n    bb6: {\n        _0 = arch::cpu::context::CpuExceptionType::FaultOrTrap;\n        goto -> bb7;\n    }\n    bb7: {\n        return;\n    }\n}\n",
  "doc": "",
  "tags": {
    "tags": [],
    "spec": {},
    "docs": []
  }
}