{
  "name": "cpu::local::is_used::debug_set_true",
  "safe": true,
  "callees": {
    "core::sync::atomic::AtomicBool::store": {
      "safe": true,
      "tags": {
        "tags": [],
        "spec": {},
        "docs": []
      },
      "doc": " Stores a value into the bool.\n\n `store` takes an [`Ordering`] argument which describes the memory ordering\n of this operation. Possible values are [`SeqCst`], [`Release`] and [`Relaxed`].\n\n # Panics\n\n Panics if `order` is [`Acquire`] or [`AcqRel`].\n\n # Examples\n\n ```\n use std::sync::atomic::{AtomicBool, Ordering};\n\n let some_bool = AtomicBool::new(true);\n\n some_bool.store(false, Ordering::Relaxed);\n assert_eq!(some_bool.load(Ordering::Relaxed), false);\n ```\n",
      "adt": {}
    }
  },
  "adts": {
    "core::sync::atomic::AtomicBool": [
      "Ref"
    ],
    "core::sync::atomic::Ordering": [
      "Plain"
    ]
  },
  "path": {
    "type": "Local",
    "path": "ostd::cpu::local::is_used::debug_set_true"
  },
  "span": "ostd/src/cpu/local/mod.rs:298:13: 300:14",
  "src": "pub fn debug_set_true() {\n                IS_USED.store(true, Ordering::Relaxed);\n            }",
  "mir": "fn cpu::local::is_used::debug_set_true() -> () {\n    let mut _0: ();\n    let  _1: ();\n    let mut _2: &core::sync::atomic::AtomicBool;\n    let mut _3: core::sync::atomic::Ordering;\n    bb0: {\n        StorageLive(_2);\n        _2 = {alloc790: &core::sync::atomic::AtomicBool};\n        StorageLive(_3);\n        _3 = core::sync::atomic::Ordering::Relaxed;\n        _1 = core::sync::atomic::AtomicBool::store(move _2, true, move _3) -> [return: bb1, unwind unreachable];\n    }\n    bb1: {\n        StorageDead(_3);\n        StorageDead(_2);\n        return;\n    }\n}\n",
  "doc": "",
  "tags": {
    "tags": [],
    "spec": {},
    "docs": []
  }
}