{
  "name": "core::<(dyn any::Any + marker::Send + 'static)>::downcast_unchecked_mut",
  "span": "$library/core/src/any.rs:459:5: 459:70",
  "safe": false,
  "callees": {
    "core::<(dyn any::Any + 'static)>::downcast_unchecked_mut": {
      "safe": false,
      "tags": {
        "tags": [],
        "spec": {},
        "docs": []
      },
      "adt": {}
    }
  },
  "adts": {},
  "path": {
    "type": "Local",
    "path": "core::<(dyn any::Any + marker::Send + 'static)>::downcast_unchecked_mut"
  },
  "tags": {
    "tags": [],
    "spec": {},
    "docs": []
  }
}