{
  "name": "core::iter::traits::iterator::Iterator::filter_map",
  "span": "$library/core/src/iter/traits/iterator.rs:938:5: 941:43",
  "safe": true,
  "callees": {
    "core::iter::adapters::filter_map::FilterMap::<I, F>::new": {
      "safe": true,
      "adt": {
        "iter::adapters::filter_map::FilterMap": "Constructor"
      }
    }
  },
  "adts": {
    "iter::adapters::filter_map::FilterMap": [
      "Plain"
    ]
  },
  "path": {
    "type": "External",
    "path": "iter::traits::iterator::Iterator::filter_map"
  }
}