{
  "name": "std::sync::lazy_lock::LazyLock::<T, F>::force_mut::really_init_mut",
  "span": "$library/std/src/sync/lazy_lock.rs:191:9: 191:92",
  "safe": false,
  "callees": {
    "core::cell::UnsafeCell::<T>::get_mut": {
      "safe": true,
      "adt": {}
    },
    "core::mem::ManuallyDrop::<T>::take": {
      "safe": false,
      "adt": {}
    },
    "core::ops::FnOnce::call_once": {
      "safe": true,
      "adt": {}
    },
    "core::mem::ManuallyDrop::<T>::new": {
      "safe": true,
      "adt": {}
    },
    "std::sync::once::Once::set_state": {
      "safe": true,
      "adt": {
        "std::sync::once::Once": {
          "kind": "MethodMutableRefReceiver",
          "field": {
            "0-inner": "Write"
          }
        }
      }
    },
    "core::mem::forget": {
      "safe": true,
      "adt": {}
    },
    "core::ops::DerefMut::deref_mut": {
      "safe": true,
      "adt": {}
    }
  },
  "adts": {
    "std::sync::lazy_lock::LazyLock": {
      "kind": "MutableAsArgument",
      "field": {
        "0-once": "Write",
        "1-data": "Write"
      }
    }
  },
  "path": {
    "type": "Local",
    "path": "std::sync::lazy_lock::LazyLock::<T, F>::force_mut::really_init_mut"
  }
}