{
  "name": "alloc::<sync::Arc<str> as core::convert::From<&str>>::from",
  "span": "$library/alloc/src/sync.rs:3941:5: 3941:33",
  "safe": true,
  "callees": {
    "core::str::<impl str>::as_bytes": {
      "safe": true,
      "adt": {}
    },
    "core::convert::From::from": {
      "safe": true,
      "adt": {}
    },
    "alloc::sync::Arc::<T>::into_raw": {
      "safe": true,
      "adt": {
        "sync::Arc": "ImmutableAsArgument"
      }
    },
    "alloc::sync::Arc::<T>::from_raw": {
      "safe": false,
      "adt": {
        "sync::Arc": "Constructor"
      }
    }
  },
  "adts": {
    "sync::Arc": [
      "Plain"
    ]
  },
  "path": {
    "type": "Local",
    "path": "alloc::<sync::Arc<str> as core::convert::From<&str>>::from"
  }
}