{
  "name": "core::iter::Cloned",
  "constructors": [],
  "access_self_as_arg": {
    "read": [],
    "write": [],
    "other": []
  },
  "access_self_as_locals": {
    "read": [],
    "write": [],
    "other": [
      "<collections::binary_heap::BinaryHeap<T, A> as core::iter::Extend<&'a T>>::extend",
      "<collections::btree::set::BTreeSet<T, A> as core::iter::Extend<&'a T>>::extend",
      "<&collections::btree::set::BTreeSet<T, A> as core::ops::Sub<&collections::btree::set::BTreeSet<T, A>>>::sub",
      "<&collections::btree::set::BTreeSet<T, A> as core::ops::BitXor<&collections::btree::set::BTreeSet<T, A>>>::bitxor",
      "<&collections::btree::set::BTreeSet<T, A> as core::ops::BitAnd<&collections::btree::set::BTreeSet<T, A>>>::bitand",
      "<&collections::btree::set::BTreeSet<T, A> as core::ops::BitOr<&collections::btree::set::BTreeSet<T, A>>>::bitor",
      "<collections::linked_list::LinkedList<T, A> as core::iter::Extend<&'a T>>::extend",
      "<collections::linked_list::LinkedList<T, A> as core::clone::Clone>::clone",
      "<collections::linked_list::LinkedList<T, A> as core::clone::Clone>::clone_from",
      "<collections::vec_deque::VecDeque<T, A> as core::clone::Clone>::clone",
      "<collections::vec_deque::VecDeque<T, A> as core::clone::Clone>::clone_from",
      "<rc::Rc<[T]> as rc::RcFromSlice<T>>::from_slice",
      "string::String::from_utf16",
      "string::String::from_utf16_lossy",
      "<string::String as core::iter::Extend<&'a char>>::extend",
      "<string::String as core::iter::Extend<&'a core::ascii::Char>>::extend",
      "<sync::Arc<[T]> as sync::ArcFromSlice<T>>::from_slice",
      "<vec::Vec<T, A> as vec::spec_extend::SpecExtend<&'a T, I>>::spec_extend",
      "wtf8::Wtf8Buf::from_wide"
    ]
  },
  "access_field": [
    {
      "read": [],
      "write": [],
      "other": []
    }
  ],
  "span": "/home/gh-zjp-CN/.rustup/toolchains/nightly-2025-12-06-aarch64-unknown-linux-gnu/lib/rustlib/src/rust/library/core/src/iter/adapters/cloned.rs:18:1: 18:21",
  "src": "pub struct Cloned<I>",
  "kind": "Struct",
  "doc_adt": " An iterator that clones the elements of an underlying iterator.\n\n This `struct` is created by the [`cloned`] method on [`Iterator`]. See its\n documentation for more.\n\n [`cloned`]: Iterator::cloned\n [`Iterator`]: trait.Iterator.html\n",
  "variant_fields": {
    "VariantIdx(None)-FieldIdx(Some(0))": {
      "name": "it",
      "doc": ""
    }
  }
}