{
  "name": "std::sys::process::env::CommandEnv::capture",
  "span": "$library/std/src/sys/process/env.rs:24:5: 24:56",
  "safe": true,
  "callees": {
    "alloc_crate::collections::BTreeMap::<K, V>::new": {
      "safe": true,
      "adt": {}
    },
    "std::env::vars_os": {
      "safe": true,
      "adt": {
        "env::VarsOs": "Constructor"
      }
    },
    "core::iter::IntoIterator::into_iter": {
      "safe": true,
      "adt": {}
    },
    "core::iter::Iterator::next": {
      "safe": true,
      "adt": {}
    },
    "core::convert::Into::into": {
      "safe": true,
      "adt": {}
    },
    "alloc_crate::collections::BTreeMap::<K, V, A>::insert": {
      "safe": true,
      "adt": {}
    },
    "core::clone::Clone::clone": {
      "safe": true,
      "adt": {}
    },
    "alloc_crate::collections::BTreeMap::<K, V, A>::remove": {
      "safe": true,
      "adt": {}
    }
  },
  "adts": {
    "alloc_crate::collections::BTreeMap": [
      "Plain",
      "MutRef",
      "Ref"
    ],
    "sys::process::env::CommandEnv": [
      "DerefVariantField(VariantIdx(None)-FieldIdx(Some(0)))",
      "DerefVariantField(VariantIdx(None)-FieldIdx(Some(2)))",
      "Ref"
    ],
    "env::VarsOs": [
      "Plain",
      "MutRef"
    ],
    "core::option::Option": [
      "Plain",
      "Unknown([Downcast(VariantIdx(1, ThreadLocalIndex)), Field(0, Ty { id: 2775, kind: RigidTy(Tuple([Ty { id: 2791, kind: RigidTy(Adt(AdtDef(DefId { id: 5580, name: \"ffi::os_str::OsString\" }), GenericArgs([]))) }, Ty { id: 2791, kind: RigidTy(Adt(AdtDef(DefId { id: 5580, name: \"ffi::os_str::OsString\" }), GenericArgs([]))) }])) }), Field(0, Ty { id: 2791, kind: RigidTy(Adt(AdtDef(DefId { id: 5580, name: \"ffi::os_str::OsString\" }), GenericArgs([]))) })])",
      "Unknown([Downcast(VariantIdx(1, ThreadLocalIndex)), Field(0, Ty { id: 2775, kind: RigidTy(Tuple([Ty { id: 2791, kind: RigidTy(Adt(AdtDef(DefId { id: 5580, name: \"ffi::os_str::OsString\" }), GenericArgs([]))) }, Ty { id: 2791, kind: RigidTy(Adt(AdtDef(DefId { id: 5580, name: \"ffi::os_str::OsString\" }), GenericArgs([]))) }])) }), Field(1, Ty { id: 2791, kind: RigidTy(Adt(AdtDef(DefId { id: 5580, name: \"ffi::os_str::OsString\" }), GenericArgs([]))) })])",
      "Unknown([Downcast(VariantIdx(1, ThreadLocalIndex)), Field(0, Ty { id: 12915, kind: RigidTy(Tuple([Ty { id: 2821, kind: RigidTy(Ref(Region { kind: ReErased }, Ty { id: 2791, kind: RigidTy(Adt(AdtDef(DefId { id: 5580, name: \"ffi::os_str::OsString\" }), GenericArgs([]))) }, Not)) }, Ty { id: 12916, kind: RigidTy(Ref(Region { kind: ReErased }, Ty { id: 2809, kind: RigidTy(Adt(AdtDef(DefId { id: 4387, name: \"core::option::Option\" }), GenericArgs([Type(Ty { id: 2791, kind: RigidTy(Adt(AdtDef(DefId { id: 5580, name: \"ffi::os_str::OsString\" }), GenericArgs([]))) })]))) }, Not)) }])) }), Field(0, Ty { id: 2821, kind: RigidTy(Ref(Region { kind: ReErased }, Ty { id: 2791, kind: RigidTy(Adt(AdtDef(DefId { id: 5580, name: \"ffi::os_str::OsString\" }), GenericArgs([]))) }, Not)) })])",
      "Ref",
      "Unknown([Downcast(VariantIdx(1, ThreadLocalIndex)), Field(0, Ty { id: 12915, kind: RigidTy(Tuple([Ty { id: 2821, kind: RigidTy(Ref(Region { kind: ReErased }, Ty { id: 2791, kind: RigidTy(Adt(AdtDef(DefId { id: 5580, name: \"ffi::os_str::OsString\" }), GenericArgs([]))) }, Not)) }, Ty { id: 12916, kind: RigidTy(Ref(Region { kind: ReErased }, Ty { id: 2809, kind: RigidTy(Adt(AdtDef(DefId { id: 4387, name: \"core::option::Option\" }), GenericArgs([Type(Ty { id: 2791, kind: RigidTy(Adt(AdtDef(DefId { id: 5580, name: \"ffi::os_str::OsString\" }), GenericArgs([]))) })]))) }, Not)) }])) }), Field(1, Ty { id: 12916, kind: RigidTy(Ref(Region { kind: ReErased }, Ty { id: 2809, kind: RigidTy(Adt(AdtDef(DefId { id: 4387, name: \"core::option::Option\" }), GenericArgs([Type(Ty { id: 2791, kind: RigidTy(Adt(AdtDef(DefId { id: 5580, name: \"ffi::os_str::OsString\" }), GenericArgs([]))) })]))) }, Not)) })])",
      "Deref",
      "Unknown([Deref, Downcast(VariantIdx(1, ThreadLocalIndex)), Field(0, Ty { id: 2791, kind: RigidTy(Adt(AdtDef(DefId { id: 5580, name: \"ffi::os_str::OsString\" }), GenericArgs([]))) })])"
    ],
    "ffi::os_str::OsString": [
      "Plain",
      "Ref"
    ],
    "alloc_crate::collections::btree_map::Iter": [
      "Plain",
      "MutRef"
    ]
  },
  "path": {
    "type": "Local",
    "path": "std::sys::process::env::CommandEnv::capture"
  }
}