{
  "name": "core::<cell::UnsafeCell<T> as convert::From<T>>::from",
  "span": "$library/core/src/cell.rs:2559:5: 2559:35",
  "safe": true,
  "callees": {
    "core::cell::UnsafeCell::<T>::new": {
      "safe": true,
      "adt": {
        "cell::UnsafeCell": {
          "kind": "Constructor",
          "field": {}
        }
      }
    }
  },
  "adts": {
    "cell::UnsafeCell": [
      "Plain"
    ]
  },
  "path": {
    "type": "Local",
    "path": "core::<cell::UnsafeCell<T> as convert::From<T>>::from"
  }
}