{
  "name": "core::num::saturating::Saturating::<i128>::leading_zeros",
  "span": "$library/core/src/num/saturating.rs:912:13: 912:52",
  "safe": true,
  "callees": {
    "core::num::<impl i128>::leading_zeros": {
      "safe": true,
      "adt": {}
    }
  },
  "adts": {
    "num::saturating::Saturating": [
      "Unknown([Field(0, Ty { id: 65, kind: RigidTy(Int(I128)) })])",
      "Plain"
    ]
  },
  "path": {
    "type": "Local",
    "path": "core::num::saturating::Saturating::<i128>::leading_zeros"
  }
}