{
  "name": "io::buffered::IntoInnerError",
  "constructors": [
    "io::buffered::bufwriter::BufWriter::<W>::into_inner",
    "io::buffered::linewriter::LineWriter::<W>::into_inner",
    "io::buffered::IntoInnerError::<W>::new",
    "io::buffered::IntoInnerError::<W>::new_wrapped"
  ],
  "access_self_as_arg": {
    "read": [
      "io::buffered::IntoInnerError::<W>::error",
      "<io::buffered::IntoInnerError<W> as core::fmt::Display>::fmt",
      "<io::buffered::IntoInnerError<W> as core::fmt::Debug>::fmt"
    ],
    "write": [],
    "other": [
      "io::buffered::IntoInnerError::<W>::new_wrapped",
      "io::buffered::IntoInnerError::<W>::into_inner",
      "io::buffered::IntoInnerError::<W>::into_error",
      "io::buffered::IntoInnerError::<W>::into_parts",
      "io::buffered::<impl core::convert::From<io::buffered::IntoInnerError<W>> for io::error::Error>::from",
      "io::buffered::IntoInnerError::<W>::new_wrapped",
      "io::buffered::IntoInnerError::<W>::into_inner",
      "io::buffered::IntoInnerError::<W>::into_error",
      "io::buffered::IntoInnerError::<W>::into_parts",
      "io::buffered::<impl core::convert::From<io::buffered::IntoInnerError<W>> for io::error::Error>::from",
      "io::buffered::IntoInnerError::<W>::new_wrapped",
      "io::buffered::IntoInnerError::<W>::into_inner",
      "io::buffered::IntoInnerError::<W>::into_error",
      "io::buffered::IntoInnerError::<W>::into_parts",
      "io::buffered::<impl core::convert::From<io::buffered::IntoInnerError<W>> for io::error::Error>::from"
    ]
  },
  "access_self_as_locals": {
    "read": [],
    "write": [],
    "other": [
      "io::buffered::bufwriter::BufWriter::<W>::into_inner",
      "io::buffered::IntoInnerError::<W>::new"
    ]
  },
  "access_field": [
    {
      "read": [],
      "write": [
        "<io::buffered::IntoInnerError<W> as core::fmt::Debug>::fmt"
      ],
      "other": []
    },
    {
      "read": [],
      "write": [
        "io::buffered::IntoInnerError::<W>::error",
        "<io::buffered::IntoInnerError<W> as core::fmt::Debug>::fmt"
      ],
      "other": []
    }
  ],
  "span": "/home/gh-zjp-CN/.rustup/toolchains/nightly-2025-12-06-aarch64-unknown-linux-gnu/lib/rustlib/src/rust/library/std/src/io/buffered/mod.rs:46:1: 46:29",
  "src": "pub struct IntoInnerError<W>",
  "kind": "Struct",
  "doc_adt": " An error returned by [`BufWriter::into_inner`] which combines an error that\n happened while writing out the buffer, and the buffered writer object\n which may be used to recover from the condition.\n\n # Examples\n\n ```no_run\n use std::io::BufWriter;\n use std::net::TcpStream;\n\n let mut stream = BufWriter::new(TcpStream::connect(\"127.0.0.1:34254\").unwrap());\n\n // do stuff with the stream\n\n // we want to get our `TcpStream` back, so let's try:\n\n let stream = match stream.into_inner() {\n     Ok(s) => s,\n     Err(e) => {\n         // Here, e is an IntoInnerError\n         panic!(\"An error occurred\");\n     }\n };\n ```\n",
  "variant_fields": {
    "VariantIdx(None)-FieldIdx(Some(0))": {
      "name": "0",
      "doc": ""
    },
    "VariantIdx(None)-FieldIdx(Some(1))": {
      "name": "1",
      "doc": ""
    }
  }
}