{
  "name": "os::unix::net::ancillary::Messages",
  "constructors": [
    "os::unix::net::ancillary::SocketAncillary::<'a>::messages"
  ],
  "access_self_as_arg": {
    "read": [],
    "write": [
      "<os::unix::net::ancillary::Messages<'a> as core::iter::Iterator>::next"
    ],
    "other": []
  },
  "access_self_as_locals": {
    "read": [],
    "write": [],
    "other": [
      "os::unix::net::ancillary::SocketAncillary::<'a>::messages"
    ]
  },
  "access_field": [
    {
      "read": [],
      "write": [
        "<os::unix::net::ancillary::Messages<'a> as core::iter::Iterator>::next"
      ],
      "other": []
    },
    {
      "read": [],
      "write": [
        "<os::unix::net::ancillary::Messages<'a> as core::iter::Iterator>::next"
      ],
      "other": []
    }
  ],
  "span": "/home/gh-zjp-CN/.rustup/toolchains/nightly-2025-12-06-aarch64-unknown-linux-gnu/lib/rustlib/src/rust/library/std/src/os/unix/net/ancillary.rs:537:1: 537:24",
  "src": "pub struct Messages<'a>",
  "kind": "Struct",
  "doc_adt": " This struct is used to iterate through the control messages.\n",
  "variant_fields": {
    "VariantIdx(None)-FieldIdx(Some(0))": {
      "name": "buffer",
      "doc": ""
    },
    "VariantIdx(None)-FieldIdx(Some(1))": {
      "name": "current",
      "doc": ""
    }
  }
}