{
  "name": "sys::process::unix::common::ExitCode",
  "constructors": [
    "<sys::process::unix::common::ExitCode as core::convert::From<u8>>::from",
    "<sys::process::unix::common::ExitCode as core::clone::Clone>::clone"
  ],
  "access_self_as_arg": {
    "read": [
      "<sys::process::unix::common::ExitCode as core::fmt::Debug>::fmt",
      "sys::process::unix::common::ExitCode::as_i32",
      "<sys::process::unix::common::ExitCode as core::cmp::PartialEq>::eq",
      "<sys::process::unix::common::ExitCode as core::cmp::Eq>::assert_receiver_is_total_eq",
      "<sys::process::unix::common::ExitCode as core::clone::Clone>::clone"
    ],
    "write": [
      "<sys::process::unix::common::ExitCode as core::clone::Clone>::clone"
    ],
    "other": [
      "<process::ExitCode as sys_common::FromInner<sys::process::unix::common::ExitCode>>::from_inner",
      "<sys::process::unix::common::ExitCode as core::clone::Clone>::clone"
    ]
  },
  "access_self_as_locals": {
    "read": [
      "process::ExitCode::to_i32",
      "<process::ExitCode as sys_common::AsInner<sys::process::unix::common::ExitCode>>::as_inner",
      "<process::ExitCode as core::fmt::Debug>::fmt",
      "<process::ExitCode as core::cmp::PartialEq>::eq"
    ],
    "write": [],
    "other": [
      "<process::ExitCode as core::convert::From<u8>>::from",
      "<sys::process::unix::common::ExitCode as core::convert::From<u8>>::from"
    ]
  },
  "access_field": [
    {
      "read": [
        "<sys::process::unix::common::ExitCode as core::fmt::Debug>::fmt",
        "sys::process::unix::common::ExitCode::as_i32",
        "<sys::process::unix::common::ExitCode as core::cmp::PartialEq>::eq"
      ],
      "write": [],
      "other": []
    }
  ],
  "span": "$library/std/src/sys/process/unix/common.rs:580:1: 580:20",
  "src": "pub struct ExitCode",
  "kind": "Struct",
  "doc_adt": "",
  "variant_fields": {
    "VariantIdx(None)-FieldIdx(Some(0))": {
      "name": "0",
      "doc": ""
    }
  }
}