{
  "name": "<[T] as fmt::Debug>::fmt",
  "safe": true,
  "callees": {
    "fmt::Formatter::<'a>::debug_list": {
      "safe": true,
      "tags": {
        "tags": [],
        "spec": {},
        "docs": []
      },
      "doc": " Creates a `DebugList` builder designed to assist with creation of\n `fmt::Debug` implementations for list-like structures.\n\n # Examples\n\n ```rust\n use std::fmt;\n\n struct Foo(Vec<i32>);\n\n impl fmt::Debug for Foo {\n     fn fmt(&self, fmt: &mut fmt::Formatter<'_>) -> fmt::Result {\n         fmt.debug_list().entries(self.0.iter()).finish()\n     }\n }\n\n assert_eq!(format!(\"{:?}\", Foo(vec![10, 11])), \"[10, 11]\");\n ```\n",
      "adt": {
        "fmt::Formatter": "MutableAsArgument",
        "fmt::builders::DebugList": "Constructor"
      }
    },
    "slice::<impl [T]>::iter": {
      "safe": true,
      "tags": {
        "tags": [],
        "spec": {},
        "docs": []
      },
      "doc": " Returns an iterator over the slice.\n\n The iterator yields all items from start to end.\n\n # Examples\n\n ```\n let x = &[1, 2, 4];\n let mut iterator = x.iter();\n\n assert_eq!(iterator.next(), Some(&1));\n assert_eq!(iterator.next(), Some(&2));\n assert_eq!(iterator.next(), Some(&4));\n assert_eq!(iterator.next(), None);\n ```\n",
      "adt": {
        "slice::iter::Iter": "Constructor"
      }
    },
    "fmt::builders::DebugList::<'a, 'b>::entries": {
      "safe": true,
      "tags": {
        "tags": [],
        "spec": {},
        "docs": []
      },
      "doc": " Adds the contents of an iterator of entries to the list output.\n\n # Examples\n\n ```\n use std::fmt;\n\n struct Foo(Vec<i32>, Vec<u32>);\n\n impl fmt::Debug for Foo {\n     fn fmt(&self, fmt: &mut fmt::Formatter<'_>) -> fmt::Result {\n         fmt.debug_list()\n            .entries(self.0.iter())\n            .entries(self.1.iter())\n            .finish()\n     }\n }\n\n assert_eq!(\n     format!(\"{:?}\", Foo(vec![10, 11], vec![12, 13])),\n     \"[10, 11, 12, 13]\",\n );\n ```\n",
      "adt": {
        "fmt::builders::DebugList": "MutableAsArgument"
      }
    },
    "fmt::builders::DebugList::<'a, 'b>::finish": {
      "safe": true,
      "tags": {
        "tags": [],
        "spec": {},
        "docs": []
      },
      "doc": " Finishes output and returns any error encountered.\n\n # Examples\n\n ```\n use std::fmt;\n\n struct Foo(Vec<i32>);\n\n impl fmt::Debug for Foo {\n     fn fmt(&self, fmt: &mut fmt::Formatter<'_>) -> fmt::Result {\n         fmt.debug_list()\n            .entries(self.0.iter())\n            .finish() // Ends the list formatting.\n     }\n }\n\n assert_eq!(\n     format!(\"{:?}\", Foo(vec![10, 11])),\n     \"[10, 11]\",\n );\n ```\n",
      "adt": {
        "fmt::builders::DebugList": "MutableAsArgument",
        "result::Result": "Constructor"
      }
    }
  },
  "adts": {
    "fmt::Formatter": [
      "MutRef"
    ],
    "fmt::builders::DebugList": [
      "Plain",
      "MutRef"
    ],
    "slice::iter::Iter": [
      "Plain"
    ],
    "result::Result": [
      "Plain"
    ]
  },
  "path": 1217,
  "span": "/home/gh-zjp-CN/.rustup/toolchains/nightly-2025-12-06-aarch64-unknown-linux-gnu/lib/rustlib/src/rust/library/core/src/fmt/mod.rs:3115:5: 3117:6",
  "src": "fn fmt(&self, f: &mut Formatter<'_>) -> Result {\n        f.debug_list().entries(self.iter()).finish()\n    }",
  "mir": "fn <[T] as fmt::Debug>::fmt(_1: &[T], _2: &mut fmt::Formatter<'_>) -> result::Result<(), fmt::Error> {\n    let mut _0: result::Result<(), fmt::Error>;\n    let mut _3: &mut fmt::builders::DebugList<'_, '_>;\n    let mut _4: &mut fmt::builders::DebugList<'_, '_>;\n    let mut _5: fmt::builders::DebugList<'_, '_>;\n    let mut _6: slice::iter::Iter<'_, T>;\n    debug self => _1;\n    debug f => _2;\n    bb0: {\n        StorageLive(_4);\n        StorageLive(_5);\n        _5 = fmt::Formatter::<'_>::debug_list(_2) -> [return: bb1, unwind unreachable];\n    }\n    bb1: {\n        _4 = &mut _5;\n        StorageLive(_6);\n        _6 = slice::<impl [T]>::iter(_1) -> [return: bb2, unwind unreachable];\n    }\n    bb2: {\n        _3 = fmt::builders::DebugList::<'_, '_>::entries::<&T, slice::iter::Iter<'_, T>>(move _4, move _6) -> [return: bb3, unwind unreachable];\n    }\n    bb3: {\n        StorageDead(_6);\n        StorageDead(_4);\n        _0 = fmt::builders::DebugList::<'_, '_>::finish(_3) -> [return: bb4, unwind unreachable];\n    }\n    bb4: {\n        StorageDead(_5);\n        return;\n    }\n}\n",
  "doc": "",
  "tags": {
    "tags": [],
    "spec": {},
    "docs": []
  }
}