{
  "name": "<sync::atomic::AtomicIsize as convert::From<isize>>::from",
  "safe": true,
  "callees": {
    "sync::atomic::AtomicIsize::new": {
      "safe": true,
      "tags": {
        "tags": [],
        "spec": {},
        "docs": []
      },
      "doc": " Creates a new atomic integer.\n\n # Examples\n\n ```\n\n ```\n",
      "adt": {
        "sync::atomic::AtomicIsize": "Constructor"
      }
    }
  },
  "adts": {
    "sync::atomic::AtomicIsize": [
      "Plain"
    ]
  },
  "path": 17330,
  "span": "/home/gh-zjp-CN/.rustup/toolchains/nightly-2025-12-06-aarch64-unknown-linux-gnu/lib/rustlib/src/rust/library/core/src/sync/atomic.rs:2657:13: 2657:59",
  "src": "fn from(v: $int_type) -> Self { Self::new(v) }",
  "mir": "fn <sync::atomic::AtomicIsize as convert::From<isize>>::from(_1: isize) -> sync::atomic::AtomicIsize {\n    let mut _0: sync::atomic::AtomicIsize;\n    debug v => _1;\n    bb0: {\n        _0 = sync::atomic::AtomicIsize::new(_1) -> [return: bb1, unwind unreachable];\n    }\n    bb1: {\n        return;\n    }\n}\n",
  "doc": "",
  "tags": {
    "tags": [],
    "spec": {},
    "docs": []
  }
}