{
  "name": "core_arch::x86::avxneconvert::_mm256_cvtneebf16_ps",
  "safe": false,
  "callees": {
    "core_arch::x86::avxneconvert::cvtneebf162ps_256": {
      "safe": false,
      "tags": {
        "tags": [],
        "spec": {},
        "docs": []
      },
      "doc": "",
      "adt": {}
    }
  },
  "adts": {
    "core_arch::x86::__m256": [
      "Plain"
    ]
  },
  "path": 11387,
  "span": "/home/gh-zjp-CN/.rustup/toolchains/nightly-2025-12-06-aarch64-unknown-linux-gnu/lib/rustlib/src/rust/library/core/src/../../stdarch/crates/core_arch/src/x86/avxneconvert.rs:79:1: 81:2",
  "src": "pub unsafe fn _mm256_cvtneebf16_ps(a: *const __m256bh) -> __m256 {\n    transmute(cvtneebf162ps_256(a))\n}",
  "mir": "fn core_arch::x86::avxneconvert::_mm256_cvtneebf16_ps(_1: *const core_arch::x86::__m256bh) -> core_arch::x86::__m256 {\n    let mut _0: core_arch::x86::__m256;\n    debug a => _1;\n    bb0: {\n        _0 = core_arch::x86::avxneconvert::cvtneebf162ps_256(_1) -> [return: bb1, unwind unreachable];\n    }\n    bb1: {\n        return;\n    }\n}\n",
  "doc": " Convert packed BF16 (16-bit) floating-point even-indexed elements stored at memory locations starting at\n location a to single precision (32-bit) floating-point elements, and store the results in dst.\n\n [Intel's documentation](https://software.intel.com/sites/landingpage/IntrinsicsGuide/#text=_mm256_cvtneebf16_ps)\n",
  "tags": {
    "tags": [],
    "spec": {},
    "docs": []
  }
}