{
  "name": "core_simd::masks::Mask::<T, N>::to_bitmask",
  "safe": true,
  "callees": {
    "core_simd::masks::mask_impl::Mask::<T, N>::to_bitmask_integer": {
      "safe": true,
      "tags": {
        "tags": [],
        "spec": {},
        "docs": []
      },
      "doc": "",
      "adt": {}
    }
  },
  "adts": {
    "core_simd::masks::mask_impl::Mask": [
      "Plain"
    ],
    "core_simd::masks::Mask": [
      "Unknown([Field(0, Ty { id: 25197, kind: RigidTy(Adt(AdtDef(DefId { id: 31096, name: \"core_simd::masks::mask_impl::Mask\" }), GenericArgs([Type(Ty { id: 95, kind: Param(ParamTy { index: 0, name: \"T\" }) }), Const(TyConst { kind: Param(ParamConst { index: 1, name: \"N\" }), id: TyConstId(37, ThreadLocalIndex) })]))) })])",
      "Plain"
    ]
  },
  "path": {
    "type": "Local",
    "path": "core::core_simd::masks::Mask::<T, N>::to_bitmask"
  },
  "span": "/home/gh-zjp-CN/.rustup/toolchains/nightly-2025-12-06-aarch64-unknown-linux-gnu/lib/rustlib/src/rust/library/core/src/../../portable-simd/crates/core_simd/src/masks.rs:297:5: 299:6",
  "src": "pub fn to_bitmask(self) -> u64 {\n        self.0.to_bitmask_integer()\n    }",
  "mir": "fn core_simd::masks::Mask::<T, N>::to_bitmask(_1: core_simd::masks::Mask<T, N>) -> u64 {\n    let mut _0: u64;\n    let mut _2: core_simd::masks::mask_impl::Mask<T, N>;\n    debug self => _1;\n    bb0: {\n        StorageLive(_2);\n        _2 = (_1.0: core_simd::masks::mask_impl::Mask<T, N>);\n        _0 = core_simd::masks::mask_impl::Mask::<T, N>::to_bitmask_integer(move _2) -> [return: bb1, unwind unreachable];\n    }\n    bb1: {\n        StorageDead(_2);\n        return;\n    }\n}\n",
  "doc": " Creates a bitmask from a mask.\n\n Each bit is set if the corresponding element in the mask is `true`.\n If the mask contains more than 64 elements, the bitmask is truncated to the first 64.\n",
  "tags": {
    "tags": [],
    "spec": {},
    "docs": []
  }
}