{
  "name": "core::mem::drop_guard::DropGuard::<T, F>::new",
  "span": "$library/core/src/mem/drop_guard.rs:60:5: 60:45",
  "safe": true,
  "callees": {
    "core::mem::manually_drop::ManuallyDrop::<T>::new": {
      "safe": true,
      "adt": {
        "mem::manually_drop::ManuallyDrop": "Constructor"
      }
    }
  },
  "adts": {
    "mem::manually_drop::ManuallyDrop": [
      "Plain"
    ],
    "mem::drop_guard::DropGuard": [
      "Plain"
    ]
  },
  "path": {
    "type": "Local",
    "path": "core::mem::drop_guard::DropGuard::<T, F>::new"
  }
}